HISTORY.rst
MANIFEST.in
README.rst
setup.py
transmogrify/__init__.py
transmogrify.sqlalchemy.egg-info/PKG-INFO
transmogrify.sqlalchemy.egg-info/SOURCES.txt
transmogrify.sqlalchemy.egg-info/dependency_links.txt
transmogrify.sqlalchemy.egg-info/namespace_packages.txt
transmogrify.sqlalchemy.egg-info/not-zip-safe
transmogrify.sqlalchemy.egg-info/requires.txt
transmogrify.sqlalchemy.egg-info/top_level.txt
transmogrify/sqlalchemy/__init__.py
transmogrify/sqlalchemy/configure.zcml
transmogrify/sqlalchemy/tests/__init__.py
transmogrify/sqlalchemy/tests/pipeline.cfg
transmogrify/sqlalchemy/tests/testSource.py
transmogrify/sqlalchemy/tests/tests.zcml
transmogrify/sqlalchemy/tests/utils.py