Metadata-Version: 1.1
Name: transmogrify.sqlalchemy
Version: 1.0.2
Summary: Feed data from SQLAlchemy into a transmogrifier pipeline
Home-page: UNKNOWN
Author: Wichert Akkerman - Jarn
Author-email: info@jarn.com
License: GPL
Keywords: transmogrify sql import
Platform: UNKNOWN
Classifier: Programming Language :: Python
Classifier: Topic :: Software Development :: Libraries :: Python Modules
